kafkaesque_pylib/__init__.py
kafkaesque_pylib/config/__init__.py
kafkaesque_pylib/config/kafkaesque_client_config.py
kafkaesque_pylib/config/kafkaesque_cluster_config.py
kafkaesque_pylib/deserializer/__init__.py
kafkaesque_pylib/deserializer/avro_deserializer.py
kafkaesque_pylib/deserializer/deserializer.py
kafkaesque_pylib/deserializer/deserializer_resolver.py
kafkaesque_pylib/deserializer/string_deserializer.py
kafkaesque_pylib/kafkaesque_config.py
kafkaesque_pylib/kafkaesque_context.py
kafkaesque_pylib/kafkaesque_error.py
kafkaesque_pylib/kafkaesque_exception.py
kafkaesque_pylib/kafkaesque_message.py
kafkaesque_pylib/kafkaesque_partitioner.py
kafkaesque_pylib/kafkaesque_topic.py
kafkaesque_pylib/tracer/__init__.py
kafkaesque_pylib/tracer/all_tracer.py
kafkaesque_pylib/tracer/continuous_tracer.py
kafkaesque_pylib/tracer/newest_tracer.py
kafkaesque_pylib/tracer/oldest_tracer.py
kafkaesque_pylib/tracer/specific_offset_tracer.py
kafkaesque_pylib/tracer/time_tracer.py
kafkaesque_pylib/tracer/tracer.py
kafkaesque_pylib/tracer/util/__init__.py
kafkaesque_pylib/tracer/util/consumer_factory.py
kafkaesque_pylib/tracer/util/message_mapper.py
kafkaesque_pylib-0.0.5.dist-info/METADATA
kafkaesque_pylib-0.0.5.dist-info/WHEEL
kafkaesque_pylib-0.0.5.dist-info/RECORD
