Metadata-Version: 2.3
Name: kafkaesque-pylib
Version: 0.0.5
Summary: 
Author: Stefan Heigl stefan.heigl90@gmail.com
Requires-Python: >=3.11,<4.0
Classifier: Programming Language :: Python :: 3
Classifier: Programming Language :: Python :: 3.11
Classifier: Programming Language :: Python :: 3.12
Classifier: Programming Language :: Python :: 3.13
Requires-Dist: confluent-kafka[avro,schemaregistry] (>=2.11.1,<3.0.0)
Requires-Dist: isodate (>=0.7,<0.8)
Requires-Dist: murmurhash2 (>=0.2.10,<0.3.0)
Requires-Dist: pyyaml (>=6.0.2,<7.0.0)
